voicely/__init__.py
voicely/code.py
voicely/translation.py
voicely/utils.py
voicely-5.0.0.dist-info/LICENSE
voicely-5.0.0.dist-info/METADATA
voicely-5.0.0.dist-info/WHEEL
voicely-5.0.0.dist-info/top_level.txt
voicely-5.0.0.dist-info/RECORD
