Metadata-Version: 2.1
Name: voicely
Version: 5.0.0
Summary: Voicely is a lightweight Python library that converts audio files → text and optionally translates the extracted text 
Author: AhMed
Author-email: asyncpy@proton.me
License: MIT
Classifier: Programming Language :: Python :: 3
Classifier: License :: OSI Approved :: MIT License
Classifier: Operating System :: OS Independent
Requires-Python: >=3.6
License-File: LICENSE
